pypickle/__init__.py
pypickle/examples.py
pypickle/pypickle.py
pypickle-2.0.1.dist-info/licenses/LICENSE
pypickle-2.0.1.dist-info/METADATA
pypickle-2.0.1.dist-info/WHEEL
pypickle-2.0.1.dist-info/top_level.txt
pypickle-2.0.1.dist-info/RECORD
