Metadata-Version: 2.4
Name: pypickle
Version: 2.0.1
Summary: pypickle is a Python library to save and load variables in pickle files.
Author-email: Erdogan Taskesen <erdogant@gmail.com>
License: MIT License
Project-URL: Homepage, https://erdogant.github.io/pypickle
Project-URL: Download, https://github.com/erdogant/pypickle/archive/{version}.tar.gz
Keywords: Python,pypi,pickle,save,load
Classifier: Programming Language :: Python :: 3
Classifier: License :: OSI Approved :: MIT License
Classifier: Operating System :: OS Independent
Classifier: Intended Audience :: Education
Classifier: Intended Audience :: Science/Research
Classifier: Operating System :: Unix
Classifier: Operating System :: Microsoft :: Windows
Classifier: Operating System :: MacOS
Requires-Python: >=3
License-File: LICENSE
Dynamic: license-file
